MANIFEST.in
setup.py
coinrpc/__init__.py
coinrpc/bitcoind_server.py
coinrpc/config.py
coinrpc/config_local.py
coinrpc/namecoind_cluster.py
coinrpc/namecoind_server.py
coinrpc.egg-info/PKG-INFO
coinrpc.egg-info/SOURCES.txt
coinrpc.egg-info/dependency_links.txt
coinrpc.egg-info/not-zip-safe
coinrpc.egg-info/requires.txt
coinrpc.egg-info/top_level.txt
coinrpc/scripts/setup_bitcoind.sh
coinrpc/scripts/setup_namecoind.sh