Metadata-Version: 1.1
Name: coinrpc
Version: 0.1.0
Summary: Bitcoind and Namecoind python-rpc
Home-page: https://github.com/onenameio/coinrpc
Author: Muneeb Ali (@muneeb) and Ibrahim Ahmed
Author-email: hello@halfmoonlabs.com
License: MIT
Keywords: python,bitcoin,namecoin,rpc
Platform: UNKNOWN
Classifier: Intended Audience :: Developers
Classifier: License :: OSI Approved :: MIT License
Classifier: Operating System :: OS Independent
Classifier: Programming Language :: Python
